openapi_drf_codegen/__init__.py
openapi_drf_codegen/codegen.py
openapi_drf_codegen/main.py
openapi_drf_codegen/utils/text_templates.py
openapi_drf_codegen/utils/types.py
openapi_drf_codegen-1.0.0.dist-info/LICENSE
openapi_drf_codegen-1.0.0.dist-info/METADATA
openapi_drf_codegen-1.0.0.dist-info/WHEEL
openapi_drf_codegen-1.0.0.dist-info/entry_points.txt
openapi_drf_codegen-1.0.0.dist-info/RECORD
